azure_recommendations_4/__init__.py
azure_recommendations_4/recommendation/__init__.py
azure_recommendations_4/recommendation/advisor_recommendations.py
azure_recommendations_4/recommendation/network_recommendations.py
azure_recommendations_4/recommendation/utils.py
azure_recommendations_4/recommendation/vm_recommendations.py
azure_recommendations_4-0.1.5.dist-info/LICENCE
azure_recommendations_4-0.1.5.dist-info/METADATA
azure_recommendations_4-0.1.5.dist-info/WHEEL
azure_recommendations_4-0.1.5.dist-info/top_level.txt
azure_recommendations_4-0.1.5.dist-info/RECORD
